irx.cpython-37m-darwin.so
IRX-0.1.3.dist-info/RECORD
IRX-0.1.3.dist-info/WHEEL
IRX-0.1.3.dist-info/top_level.txt
IRX-0.1.3.dist-info/METADATA
