Metadata-Version: 2.1
Name: IRX
Version: 0.1.3
Summary: The IR Interface package
Home-page: UNKNOWN
Author: Integrated Reasoning, Inc.
License: MIT
Platform: UNKNOWN
